pydomainextractor-0.13.9.dist-info/METADATA
pydomainextractor-0.13.9.dist-info/WHEEL
pydomainextractor-0.13.9.dist-info/license_files/LICENSE
pydomainextractor/pydomainextractor.pyi
pydomainextractor/__init__.py
pydomainextractor/pydomainextractor.cp39-win_amd64.pyd
pydomainextractor-0.13.9.dist-info/RECORD
