Metadata-Version: 2.1
Name: pydomainextractor
Version: 0.13.9
Classifier: License :: OSI Approved :: MIT License
Classifier: Operating System :: MacOS
Classifier: Operating System :: Microsoft
Classifier: Operating System :: POSIX :: Linux
Classifier: Programming Language :: Python :: 3.7
Classifier: Programming Language :: Python :: 3.8
Classifier: Programming Language :: Python :: 3.9
Classifier: Programming Language :: Python :: 3.10
Classifier: Programming Language :: Python :: 3.11
Classifier: Programming Language :: Rust
License-File: LICENSE
Keywords: domain,extraction,tld,suffix,psl,rust,pyo3
Home-Page: https://github.com/intsights/pydomainextractor
Author: Viktor Vilskyi
Author-email: viktor_vilskyi@rapid7.com
License: MIT
Requires-Python: >=3.7
Project-URL: repository, https://github.com/intsights/pydomainextractor
Project-URL: homepage, https://github.com/intsights/pydomainextractor
